led_matrix_zmq/__init__.py
led_matrix_zmq/_consts.py
led_matrix_zmq/_messages.py
led_matrix_zmq/_zmq.py
led_matrix_zmq/control.py
led_matrix_zmq/exceptions.py
led_matrix_zmq/frame.py
led_matrix_zmq/matrix.py
led_matrix_zmq/py.typed
led_matrix_zmq-1.1.0.dist-info/METADATA
led_matrix_zmq-1.1.0.dist-info/WHEEL
led_matrix_zmq-1.1.0.dist-info/licenses/LICENSE
led_matrix_zmq-1.1.0.dist-info/RECORD
