Metadata-Version: 2.4
Name: led-matrix-zmq
Version: 1.1.0
Summary: Library for interacting with led-matrix-zmq
Project-URL: source, https://github.com/Knifa/led-matrix-zmq-py
Author-email: Dan <knifa@users.noreply.github.com>
License-File: LICENSE
Classifier: Intended Audience :: Developers
Classifier: License :: OSI Approved :: GNU General Public License v3 (GPLv3)
Classifier: Operating System :: OS Independent
Classifier: Programming Language :: Python :: 3
Requires-Python: >=3.12
Requires-Dist: pyzmq>=26.2.0
